[
  {
    "id": "frame_1757929174727",
    "url": "https://i.postimg.cc/jjTJY1qT/kuku1.gif",
    "name": "头像框-1757929174727",
    "scale": 1,
    "offsetX": 0,
    "offsetY": 0
  },
  {
    "id": "frame_1757929175742",
    "url": "https://i.postimg.cc/dVrTXFYn/kuku10.gif",
    "name": "头像框-1757929175742",
    "scale": 1,
    "offsetX": 0,
    "offsetY": 0
  },
  {
    "id": "frame_1757929176161",
    "url": "https://i.postimg.cc/431Hf1n9/kuku100.gif",
    "name": "头像框-1757929176161",
    "scale": 1,
    "offsetX": 0,
    "offsetY": 0
  },
  {
    "id": "frame_1757929176437",
    "url": "https://i.postimg.cc/tCLx2TLY/kuku101.gif",
    "name": "头像框-1757929176437",
    "scale": 1,
    "offsetX": 0,
    "offsetY": 0
  },
  {
    "id": "frame_1757929177420",
    "url": "https://i.postimg.cc/MTKMvjjr/kuku102.gif",
    "name": "头像框-1757929177420",
    "scale": 1,
    "offsetX": 0,
    "offsetY": 0
  },
  {
    "id": "frame_1757929177831",
    "url": "https://i.postimg.cc/SsTX8N6Q/kuku103.gif",
    "name": "头像框-1757929177831",
    "scale": 1,
    "offsetX": 0,
    "offsetY": 0
  },
  {
    "id": "frame_1757929178357",
    "url": "https://i.postimg.cc/Wzdd7L8G/kuku104.gif",
    "name": "头像框-1757929178357",
    "scale": 1,
    "offsetX": 0,
    "offsetY": 0
  },
  {
    "id": "frame_1757929179270",
    "url": "https://i.postimg.cc/C59zPPrW/kuku105.gif",
    "name": "头像框-1757929179270",
    "scale": 1,
    "offsetX": 0,
    "offsetY": 0
  },
  {
    "id": "frame_1757929179671",
    "url": "https://i.postimg.cc/SQP2xRQD/kuku106.gif",
    "name": "头像框-1757929179671",
    "scale": 1,
    "offsetX": 0,
    "offsetY": 0
  },
  {
    "id": "frame_1757929180073",
    "url": "https://i.postimg.cc/jdJWwTLK/kuku107.gif",
    "name": "头像框-1757929180073",
    "scale": 1,
    "offsetX": 0,
    "offsetY": 0
  },
  {
    "id": "frame_1757929181008",
    "url": "https://i.postimg.cc/mgfP7nH9/kuku108.gif",
    "name": "头像框-1757929181008",
    "scale": 1,
    "offsetX": 0,
    "offsetY": 0
  },
  {
    "id": "frame_1757929181531",
    "url": "https://i.postimg.cc/VNz5Vb4L/kuku109.gif",
    "name": "头像框-1757929181531",
    "scale": 1,
    "offsetX": 0,
    "offsetY": 0
  },
  {
    "id": "frame_1757929181949",
    "url": "https://i.postimg.cc/XvxXS7DK/kuku11.gif",
    "name": "头像框-1757929181949",
    "scale": 1,
    "offsetX": 0,
    "offsetY": 0
  },
  {
    "id": "frame_1757929182945",
    "url": "https://i.postimg.cc/8zRj4bR0/kuku110.gif",
    "name": "头像框-1757929182945",
    "scale": 1,
    "offsetX": 0,
    "offsetY": 0
  },
  {
    "id": "frame_1757929183373",
    "url": "https://i.postimg.cc/qRRqkV9P/kuku111.gif",
    "name": "头像框-1757929183373",
    "scale": 1,
    "offsetX": 0,
    "offsetY": 0
  },
  {
    "id": "frame_1757929183837",
    "url": "https://i.postimg.cc/0QBQjXvb/kuku112.gif",
    "name": "头像框-1757929183837",
    "scale": 1,
    "offsetX": 0,
    "offsetY": 0
  },
  {
    "id": "frame_1757929184906",
    "url": "https://i.postimg.cc/sxG2hPfK/kuku113.gif",
    "name": "头像框-1757929184906",
    "scale": 1,
    "offsetX": 0,
    "offsetY": 0
  },
  {
    "id": "frame_1757929185620",
    "url": "https://i.postimg.cc/6TspL7yK/kuku114.gif",
    "name": "头像框-1757929185620",
    "scale": 1,
    "offsetX": 0,
    "offsetY": 0
  },
  {
    "id": "frame_1757929186046",
    "url": "https://i.postimg.cc/ZYWPc1Cs/kuku115.gif",
    "name": "头像框-1757929186046",
    "scale": 1,
    "offsetX": 0,
    "offsetY": 0
  },
  {
    "id": "frame_1757929187416",
    "url": "https://i.postimg.cc/44j6FBcf/kuku116.gif",
    "name": "头像框-1757929187416",
    "scale": 1,
    "offsetX": 0,
    "offsetY": 0
  },
  {
    "id": "frame_1757929188459",
    "url": "https://i.postimg.cc/3JpXMmjg/kuku117.gif",
    "name": "头像框-1757929188459",
    "scale": 1,
    "offsetX": 0,
    "offsetY": 0
  },
  {
    "id": "frame_1757929189118",
    "url": "https://i.postimg.cc/dVY8J3ng/kuku118.gif",
    "name": "头像框-1757929189118",
    "scale": 1,
    "offsetX": 0,
    "offsetY": 0
  },
  {
    "id": "frame_1757929190084",
    "url": "https://i.postimg.cc/g2H3jpTj/kuku119.gif",
    "name": "头像框-1757929190084",
    "scale": 1,
    "offsetX": 0,
    "offsetY": 0
  },
  {
    "id": "frame_1757929190558",
    "url": "https://i.postimg.cc/Jh7ZBFfq/kuku12.gif",
    "name": "头像框-1757929190558",
    "scale": 1,
    "offsetX": 0,
    "offsetY": 0
  },
  {
    "id": "frame_1757929191174",
    "url": "https://i.postimg.cc/wBWJ5VHd/kuku120.gif",
    "name": "头像框-1757929191174",
    "scale": 1,
    "offsetX": 0,
    "offsetY": 0
  },
  {
    "id": "frame_1757929192074",
    "url": "https://i.postimg.cc/26VW0Z8L/kuku121.gif",
    "name": "头像框-1757929192074",
    "scale": 1,
    "offsetX": 0,
    "offsetY": 0
  },
  {
    "id": "frame_1757929192537",
    "url": "https://i.postimg.cc/HxRyRkVZ/kuku122.gif",
    "name": "头像框-1757929192537",
    "scale": 1,
    "offsetX": 0,
    "offsetY": 0
  },
  {
    "id": "frame_1757929192966",
    "url": "https://i.postimg.cc/C58qgp8F/kuku123.gif",
    "name": "头像框-1757929192966",
    "scale": 1,
    "offsetX": 0,
    "offsetY": 0
  },
  {
    "id": "frame_1757929194176",
    "url": "https://i.postimg.cc/2jLvvhKP/kuku124.gif",
    "name": "头像框-1757929194176",
    "scale": 1,
    "offsetX": 0,
    "offsetY": 0
  },
  {
    "id": "frame_1757929194747",
    "url": "https://i.postimg.cc/ZKkNL0k0/kuku125.gif",
    "name": "头像框-1757929194747",
    "scale": 1,
    "offsetX": 0,
    "offsetY": 0
  },
  {
    "id": "frame_1757929195170",
    "url": "https://i.postimg.cc/QxpTYssm/kuku126.gif",
    "name": "头像框-1757929195170",
    "scale": 1,
    "offsetX": 0,
    "offsetY": 0
  },
  {
    "id": "frame_1757929196078",
    "url": "https://i.postimg.cc/2SrBPJSD/kuku127.gif",
    "name": "头像框-1757929196078",
    "scale": 1,
    "offsetX": 0,
    "offsetY": 0
  },
  {
    "id": "frame_1757929196677",
    "url": "https://i.postimg.cc/Z5HyZcWy/kuku128.gif",
    "name": "头像框-1757929196677",
    "scale": 1,
    "offsetX": 0,
    "offsetY": 0
  },
  {
    "id": "frame_1757929197125",
    "url": "https://i.postimg.cc/cJJtJn3k/kuku129.gif",
    "name": "头像框-1757929197125",
    "scale": 1,
    "offsetX": 0,
    "offsetY": 0
  },
  {
    "id": "frame_1757929198072",
    "url": "https://i.postimg.cc/B6rjN7VR/kuku13.gif",
    "name": "头像框-1757929198072",
    "scale": 1,
    "offsetX": 0,
    "offsetY": 0
  },
  {
    "id": "frame_1757929198487",
    "url": "https://i.postimg.cc/sXQBYCwp/kuku130.gif",
    "name": "头像框-1757929198487",
    "scale": 1,
    "offsetX": 0,
    "offsetY": 0
  },
  {
    "id": "frame_1757929198982",
    "url": "https://i.postimg.cc/HLPc8k4Y/kuku131.gif",
    "name": "头像框-1757929198982",
    "scale": 1,
    "offsetX": 0,
    "offsetY": 0
  },
  {
    "id": "frame_1757929199931",
    "url": "https://i.postimg.cc/wMD7rcKM/kuku132.gif",
    "name": "头像框-1757929199931",
    "scale": 1,
    "offsetX": 0,
    "offsetY": 0
  },
  {
    "id": "frame_1757929200369",
    "url": "https://i.postimg.cc/BZFLts83/kuku133.gif",
    "name": "头像框-1757929200369",
    "scale": 1,
    "offsetX": 0,
    "offsetY": 0
  },
  {
    "id": "frame_1757929200764",
    "url": "https://i.postimg.cc/28fqZJvZ/kuku134.gif",
    "name": "头像框-1757929200764",
    "scale": 1,
    "offsetX": 0,
    "offsetY": 0
  },
  {
    "id": "frame_1757929202182",
    "url": "https://i.postimg.cc/pXYmYZY1/kuku135.gif",
    "name": "头像框-1757929202182",
    "scale": 1,
    "offsetX": 0,
    "offsetY": 0
  },
  {
    "id": "frame_1757929202620",
    "url": "https://i.postimg.cc/kgJBjbTM/kuku136.gif",
    "name": "头像框-1757929202620",
    "scale": 1,
    "offsetX": 0,
    "offsetY": 0
  },
  {
    "id": "frame_1757929203063",
    "url": "https://i.postimg.cc/wjw3njrX/kuku137.gif",
    "name": "头像框-1757929203063",
    "scale": 1,
    "offsetX": 0,
    "offsetY": 0
  },
  {
    "id": "frame_1757929204068",
    "url": "https://i.postimg.cc/FK11vQt2/kuku138.gif",
    "name": "头像框-1757929204068",
    "scale": 1,
    "offsetX": 0,
    "offsetY": 0
  },
  {
    "id": "frame_1757929204563",
    "url": "https://i.postimg.cc/zfMvXP83/kuku139.gif",
    "name": "头像框-1757929204563",
    "scale": 1,
    "offsetX": 0,
    "offsetY": 0
  },
  {
    "id": "frame_1757929204959",
    "url": "https://i.postimg.cc/SsMsX7xd/kuku14.gif",
    "name": "头像框-1757929204959",
    "scale": 1,
    "offsetX": 0,
    "offsetY": 0
  },
  {
    "id": "frame_1757929205889",
    "url": "https://i.postimg.cc/prMdKh9H/kuku140.gif",
    "name": "头像框-1757929205889",
    "scale": 1,
    "offsetX": 0,
    "offsetY": 0
  },
  {
    "id": "frame_1757929206335",
    "url": "https://i.postimg.cc/fTZLLdn7/kuku141.gif",
    "name": "头像框-1757929206335",
    "scale": 1,
    "offsetX": 0,
    "offsetY": 0
  },
  {
    "id": "frame_1757929206736",
    "url": "https://i.postimg.cc/J03zxrJB/kuku142.gif",
    "name": "头像框-1757929206736",
    "scale": 1,
    "offsetX": 0,
    "offsetY": 0
  },
  {
    "id": "frame_1757929207702",
    "url": "https://i.postimg.cc/y60xsP5Y/kuku143.gif",
    "name": "头像框-1757929207702",
    "scale": 1,
    "offsetX": 0,
    "offsetY": 0
  },
  {
    "id": "frame_1757929208189",
    "url": "https://i.postimg.cc/g222yP0n/kuku144.gif",
    "name": "头像框-1757929208189",
    "scale": 1,
    "offsetX": 0,
    "offsetY": 0
  },
  {
    "id": "frame_1757929208596",
    "url": "https://i.postimg.cc/bwVN3FGL/kuku145.gif",
    "name": "头像框-1757929208596",
    "scale": 1,
    "offsetX": 0,
    "offsetY": 0
  },
  {
    "id": "frame_1757929209575",
    "url": "https://i.postimg.cc/QxbMWMh2/kuku146.gif",
    "name": "头像框-1757929209575",
    "scale": 1,
    "offsetX": 0,
    "offsetY": 0
  },
  {
    "id": "frame_1757929209972",
    "url": "https://i.postimg.cc/rpdybCxT/kuku147.gif",
    "name": "头像框-1757929209972",
    "scale": 1,
    "offsetX": 0,
    "offsetY": 0
  },
  {
    "id": "frame_1757929210443",
    "url": "https://i.postimg.cc/25Pjfb7Z/kuku148.gif",
    "name": "头像框-1757929210443",
    "scale": 1,
    "offsetX": 0,
    "offsetY": 0
  },
  {
    "id": "frame_1757929211371",
    "url": "https://i.postimg.cc/4dVf4fWF/kuku149.gif",
    "name": "头像框-1757929211371",
    "scale": 1,
    "offsetX": 0,
    "offsetY": 0
  },
  {
    "id": "frame_1757929211794",
    "url": "https://i.postimg.cc/rs9qWhX1/kuku15.gif",
    "name": "头像框-1757929211794",
    "scale": 1,
    "offsetX": 0,
    "offsetY": 0
  },
  {
    "id": "frame_1757929212199",
    "url": "https://i.postimg.cc/3NhKds6r/kuku150.gif",
    "name": "头像框-1757929212199",
    "scale": 1,
    "offsetX": 0,
    "offsetY": 0
  },
  {
    "id": "frame_1757929213250",
    "url": "https://i.postimg.cc/HspYHCXB/kuku151.gif",
    "name": "头像框-1757929213250",
    "scale": 1,
    "offsetX": 0,
    "offsetY": 0
  },
  {
    "id": "frame_1757929214020",
    "url": "https://i.postimg.cc/YqbpCyxk/kuku152.gif",
    "name": "头像框-1757929214020",
    "scale": 1,
    "offsetX": 0,
    "offsetY": 0
  },
  {
    "id": "frame_1757929214536",
    "url": "https://i.postimg.cc/L85mYByP/kuku153.gif",
    "name": "头像框-1757929214536",
    "scale": 1,
    "offsetX": 0,
    "offsetY": 0
  },
  {
    "id": "frame_1757929215468",
    "url": "https://i.postimg.cc/kgHqx6Zp/kuku154.gif",
    "name": "头像框-1757929215468",
    "scale": 1,
    "offsetX": 0,
    "offsetY": 0
  },
  {
    "id": "frame_1757929215874",
    "url": "https://i.postimg.cc/nLQZTVfc/kuku155.gif",
    "name": "头像框-1757929215874",
    "scale": 1,
    "offsetX": 0,
    "offsetY": 0
  },
  {
    "id": "frame_1757929216335",
    "url": "https://i.postimg.cc/C1T02ywC/kuku156.gif",
    "name": "头像框-1757929216335",
    "scale": 1,
    "offsetX": 0,
    "offsetY": 0
  },
  {
    "id": "frame_1757929217336",
    "url": "https://i.postimg.cc/Kjm2ZnkR/kuku157.gif",
    "name": "头像框-1757929217336",
    "scale": 1,
    "offsetX": 0,
    "offsetY": 0
  },
  {
    "id": "frame_1757929217733",
    "url": "https://i.postimg.cc/xCvQDsdw/kuku158.gif",
    "name": "头像框-1757929217733",
    "scale": 1,
    "offsetX": 0,
    "offsetY": 0
  },
  {
    "id": "frame_1757929218206",
    "url": "https://i.postimg.cc/fy5hkJm5/kuku159.gif",
    "name": "头像框-1757929218206",
    "scale": 1,
    "offsetX": 0,
    "offsetY": 0
  },
  {
    "id": "frame_1757929219163",
    "url": "https://i.postimg.cc/TYY6FJvs/kuku16.gif",
    "name": "头像框-1757929219163",
    "scale": 1,
    "offsetX": 0,
    "offsetY": 0
  },
  {
    "id": "frame_1757929219663",
    "url": "https://i.postimg.cc/RCTmgbyf/kuku160.gif",
    "name": "头像框-1757929219663",
    "scale": 1,
    "offsetX": 0,
    "offsetY": 0
  },
  {
    "id": "frame_1757929220118",
    "url": "https://i.postimg.cc/TY7665R3/kuku161.gif",
    "name": "头像框-1757929220118",
    "scale": 1,
    "offsetX": 0,
    "offsetY": 0
  },
  {
    "id": "frame_1757929221269",
    "url": "https://i.postimg.cc/138Z5Rtc/kuku162.gif",
    "name": "头像框-1757929221269",
    "scale": 1,
    "offsetX": 0,
    "offsetY": 0
  },
  {
    "id": "frame_1757929221885",
    "url": "https://i.postimg.cc/Z5Xz9kvk/kuku163.gif",
    "name": "头像框-1757929221885",
    "scale": 1,
    "offsetX": 0,
    "offsetY": 0
  },
  {
    "id": "frame_1757929222348",
    "url": "https://i.postimg.cc/43tkV8pY/kuku164.gif",
    "name": "头像框-1757929222348",
    "scale": 1,
    "offsetX": 0,
    "offsetY": 0
  },
  {
    "id": "frame_1757929223528",
    "url": "https://i.postimg.cc/Y9f5yhnk/kuku165.gif",
    "name": "头像框-1757929223528",
    "scale": 1,
    "offsetX": 0,
    "offsetY": 0
  },
  {
    "id": "frame_1757929223968",
    "url": "https://i.postimg.cc/prWwNR4j/kuku166.gif",
    "name": "头像框-1757929223968",
    "scale": 1,
    "offsetX": 0,
    "offsetY": 0
  },
  {
    "id": "frame_1757929224442",
    "url": "https://i.postimg.cc/V68yRjFD/kuku167.gif",
    "name": "头像框-1757929224442",
    "scale": 1,
    "offsetX": 0,
    "offsetY": 0
  },
  {
    "id": "frame_1757929225447",
    "url": "https://i.postimg.cc/mkm0BKW5/kuku168.gif",
    "name": "头像框-1757929225447",
    "scale": 1,
    "offsetX": 0,
    "offsetY": 0
  },
  {
    "id": "frame_1757929225865",
    "url": "https://i.postimg.cc/v8XRrxxt/kuku169.gif",
    "name": "头像框-1757929225865",
    "scale": 1,
    "offsetX": 0,
    "offsetY": 0
  },
  {
    "id": "frame_1757929226278",
    "url": "https://i.postimg.cc/zXP9MmjL/kuku17.gif",
    "name": "头像框-1757929226278",
    "scale": 1,
    "offsetX": 0,
    "offsetY": 0
  },
  {
    "id": "frame_1757929227620",
    "url": "https://i.postimg.cc/cLgVGD9F/kuku170.gif",
    "name": "头像框-1757929227620",
    "scale": 1,
    "offsetX": 0,
    "offsetY": 0
  },
  {
    "id": "frame_1757929228039",
    "url": "https://i.postimg.cc/YqS5b21K/kuku171.gif",
    "name": "头像框-1757929228039",
    "scale": 1,
    "offsetX": 0,
    "offsetY": 0
  },
  {
    "id": "frame_1757929228459",
    "url": "https://i.postimg.cc/fRG1zx1D/kuku172.gif",
    "name": "头像框-1757929228459",
    "scale": 1,
    "offsetX": 0,
    "offsetY": 0
  },
  {
    "id": "frame_1757929229391",
    "url": "https://i.postimg.cc/HLbRVrC5/kuku173.gif",
    "name": "头像框-1757929229391",
    "scale": 1,
    "offsetX": 0,
    "offsetY": 0
  },
  {
    "id": "frame_1757929229945",
    "url": "https://i.postimg.cc/G2rNYbcf/kuku174.gif",
    "name": "头像框-1757929229945",
    "scale": 1,
    "offsetX": 0,
    "offsetY": 0
  },
  {
    "id": "frame_1757929230376",
    "url": "https://i.postimg.cc/B6gzBRbn/kuku175.gif",
    "name": "头像框-1757929230376",
    "scale": 1,
    "offsetX": 0,
    "offsetY": 0
  },
  {
    "id": "frame_1757929231804",
    "url": "https://i.postimg.cc/D0wMj54d/kuku176.gif",
    "name": "头像框-1757929231804",
    "scale": 1,
    "offsetX": 0,
    "offsetY": 0
  },
  {
    "id": "frame_1757929232559",
    "url": "https://i.postimg.cc/sxH0tSpF/kuku177.gif",
    "name": "头像框-1757929232559",
    "scale": 1,
    "offsetX": 0,
    "offsetY": 0
  }
]